./PKG-INFO
./README.md
./README_EN.md
./README_ZH-TW.md
./__init__.py
./pyproject.toml
./server.py
./setup.py
./.github/workflows/pypi-publish.yml
bach_sms_verify3-1.0.1.dist-info/METADATA
bach_sms_verify3-1.0.1.dist-info/WHEEL
bach_sms_verify3-1.0.1.dist-info/entry_points.txt
bach_sms_verify3-1.0.1.dist-info/RECORD
