Metadata-Version: 2.4
Name: bach-sms_verify3
Version: 1.0.1
Summary: RapidAPI: Glavier/sms-verify3
Project-URL: Homepage, https://github.com/bachstudio/bach-sms_verify3
Project-URL: Repository, https://github.com/bachstudio/bach-sms_verify3
Project-URL: Documentation, https://github.com/bachstudio/bach-sms_verify3#readme
Requires-Python: >=3.10
Requires-Dist: fastmcp>=2.0.0
Requires-Dist: httpx>=0.25.0
Provides-Extra: dev
Requires-Dist: black>=23.0.0; extra == 'dev'
Requires-Dist: pytest>=7.0.0; extra == 'dev'
